amqtt_db/__init__.py
amqtt_db/base/__init__.py
amqtt_db/base/base_db.py
amqtt_db/base/base_decoder.py
amqtt_db/base/base_deserializer.py
amqtt_db/base/base_plugin.py
amqtt_db/base/base_structure.py
amqtt_db/base/base_topic.py
amqtt_db/base/constants.py
amqtt_db/base/delegator.py
amqtt_db/base/errors.py
amqtt_db/base/type_mapper.py
amqtt_db/base/utils.py
amqtt_db/db/__init__.py
amqtt_db/db/base.py
amqtt_db/db/db_sa.py
amqtt_db/default_config.yaml
amqtt_db/payload/__init__.py
amqtt_db/payload/flat_deserializer.py
amqtt_db/payload/json_decoder.py
amqtt_db/plugin.py
amqtt_db/startup.py
amqtt_db/structure/__init__.py
amqtt_db/structure/structure.py
amqtt_db/tests/__init__.py
amqtt_db/tests/resources/mockups.py
amqtt_db/tests/test_db/__init__.py
amqtt_db/tests/test_db/test_sa.py
amqtt_db/tests/test_plugin/__init__.py
amqtt_db/tests/test_plugin/test_functional.py
amqtt_db/tests/test_plugin/test_plugin.py
amqtt_db-0.1.5.dist-info/LICENSE
amqtt_db-0.1.5.dist-info/METADATA
amqtt_db-0.1.5.dist-info/WHEEL
amqtt_db-0.1.5.dist-info/entry_points.txt
amqtt_db-0.1.5.dist-info/RECORD
