Metadata-Version: 2.1
Name: amqtt_db
Version: 0.1.5
Summary: 
Home-page: https://github.com/volkerjaenisch/amqtt_db
License: MIT
Keywords: amqtt,MQTT,Persistence,SQLAlchemy,Database
Author: volker
Author-email: volker.jaenisch@inqbus.de
Requires-Python: >=3.7,<4.0
Classifier: Environment :: Console
Classifier: License :: OSI Approved :: MIT License
Classifier: Operating System :: OS Independent
Classifier: Programming Language :: Python :: 3
Classifier: Programming Language :: Python :: 3.7
Classifier: Programming Language :: Python :: 3.8
Classifier: Programming Language :: Python :: 3.9
Classifier: Programming Language :: Python :: 3.10
Classifier: Programming Language :: Python :: 3.11
Classifier: Programming Language :: Python :: 3.12
Requires-Dist: PyYAML (>=6.0.0,<7.0.0)
Requires-Dist: SQLAlchemy (>=1.4.1,<2.0.0)
Requires-Dist: aiounittest (>=1.4.2,<2.0.0)
Requires-Dist: psycopg2-binary (>=2.9.9,<3.0.0)
Requires-Dist: typed-ast (>=1.5.5,<2.0.0)
Requires-Dist: wrapt (>=1.14.0,<2.0.0)
Project-URL: Repository, https://github.com/volkerjaenisch/amqtt_db
